kentcbs/__init__.py
kentcbs/common.py
kentcbs/kentcbs.py
kentcbs-0.0.1.dist-info/LICENSE
kentcbs-0.0.1.dist-info/METADATA
kentcbs-0.0.1.dist-info/WHEEL
kentcbs-0.0.1.dist-info/entry_points.txt
kentcbs-0.0.1.dist-info/top_level.txt
kentcbs-0.0.1.dist-info/RECORD
